iotile_support_con_nrf52832_4/__init__.py
iotile_support_con_nrf52832_4/nrf52832_controller.py
iotile_support_con_nrf52832_4-4.1.3.dist-info/METADATA
iotile_support_con_nrf52832_4-4.1.3.dist-info/WHEEL
iotile_support_con_nrf52832_4-4.1.3.dist-info/entry_points.txt
iotile_support_con_nrf52832_4-4.1.3.dist-info/top_level.txt
iotile_support_con_nrf52832_4-4.1.3.dist-info/RECORD
