Metadata-Version: 2.1
Name: iotile-support-con-nrf52832-4
Version: 4.1.3
Summary: UNKNOWN
Home-page: UNKNOWN
Author: Arch
Author-email: info@arch-iot.com
License: UNKNOWN
Platform: UNKNOWN
Requires-Dist: iotile-support-lib-controller-4 (==4.*,>=4.3.6)
